corpusit-0.2.1.dist-info/METADATA
corpusit-0.2.1.dist-info/WHEEL
corpusit-0.2.1.dist-info/licenses/LICENSE
corpusit/__init__.py
corpusit/__init__.pyi
corpusit/corpusit.pypy38-pp73-x86_64-linux-gnu.so
corpusit/py.typed
corpusit-0.2.1.dist-info/RECORD
