Metadata-Version: 2.4
Name: corpusit
Version: 0.2.1
Classifier: Programming Language :: Rust
Classifier: Programming Language :: Python :: Implementation :: CPython
Classifier: Programming Language :: Python :: Implementation :: PyPy
License-File: LICENSE
Keywords: natural language modeling,corpus,skipgram
Author: Xin Du
Author-email: duxin.ac@gmail.com
Requires-Python: >=3.6
Project-URL: homepage, https://github.com/kduxin/corpusit
